readmebro/__init__.py
readmebro/cli.py
readmebro/decorator.py
readmebro/linking.py
readmebro-1.2.0.dist-info/licenses/LICENSE
readmebro-1.2.0.dist-info/METADATA
readmebro-1.2.0.dist-info/WHEEL
readmebro-1.2.0.dist-info/entry_points.txt
readmebro-1.2.0.dist-info/top_level.txt
readmebro-1.2.0.dist-info/RECORD
