Metadata-Version: 2.4
Name: readmebro
Version: 1.2.0
Summary: AI-powered and AI-optional Python documentation generator
Author-email: Samartha Siddhartha <samartha.siddhartha@gmail.com>
License: MIT
Project-URL: Homepage, https://github.com/samartha-siddhartha/readmebro
Project-URL: Bug Tracker, https://github.com/samartha-siddhartha/readmebro/issues
Keywords: documentation,code-analysis,readme,AI,ollama,codellama
Requires-Python: >=3.8
License-File: LICENSE
Requires-Dist: click>=8.1.3
Requires-Dist: requests>=2.31.0
Requires-Dist: yaspin>=2.2.0
Requires-Dist: networkx<4.0,>=3.1
Requires-Dist: pyvis<0.4.0,>=0.3.2
Provides-Extra: ai
Requires-Dist: ollama>=0.1.0; extra == "ai"
Dynamic: license-file
